observedstruct/__init__.py
observedstruct-0.1.0.dist-info/WHEEL
observedstruct-0.1.0.dist-info/METADATA
observedstruct-0.1.0.dist-info/RECORD
