Metadata-Version: 2.1
Name: observedstruct
Version: 0.1.0
Summary: Observed structures that calls callback functions on changes.
Home-page: https://github.com/jpmelos/observedstruct
License: MIT
Keywords: data structures
Author: João Sampaio
Author-email: jpmelos@gmail.com
Requires-Python: >=3.7,<3.10
Classifier: Development Status :: 4 - Beta
Classifier: Intended Audience :: Developers
Classifier: License :: OSI Approved :: MIT License
Classifier: Operating System :: OS Independent
Classifier: Programming Language :: Python :: 3
Classifier: Programming Language :: Python :: 3.7
Classifier: Programming Language :: Python :: 3.8
Classifier: Programming Language :: Python :: 3.9
Project-URL: Documentation, https://github.com/jpmelos/observedstruct
Project-URL: Repository, https://github.com/jpmelos/observedstruct
